{
    "products":[{"name":"Classic Beef Burger",
            "price":8.99,
            "description":"Premium beef patty with cheddar cheese,lettuce,...",
            "img":"./../assets/media/beef-burger.jpg",
            "category":"BURGERS"},
            {"name":"Double Bacon Melt",
            "price":12.50,
            "description":"Two patties, crispy bacon, melted swiss chese, and ...",
            "img":"./../assets/media/bacon-burger.jpg",
            "category":"BURGERS"},
            {"name":"Golden Fries",
            "price":3.99,
            "description":"Freshly cut potatoes fried to perfection with sea salt.",
            "img":"./../assets/media/fries.jpg",
            "category":"SIDES"},
            {"name":"Cola Zero",
            "price":2.50,
            "description":"Chilled zero sugar cola with ice and a slice of lemon",
            "img":"./../assets/media/cola.jpg",
            "category":"DRINKS"},
            {"name":"Donut Box",
            "price":6.00,
            "description":"Assorted glazed and frosted donuts.",
            "img":"./../assets/media/donuts.jpg",
            "category":"DESSERTS"},
            {"name":"Pepperoni Slice",
            "price":4.50,
            "description":"Large NY style slice with double pepperoni",
            "img":"./../assets/media/pizza.jpg",
            "category":"PIZZA"}
    ]
}